flask_ueditor/__about__.py
flask_ueditor/__init__.py
flask_ueditor/__main__.py
flask_ueditor/action.py
flask_ueditor/action_map.py
flask_ueditor/app_info.py
flask_ueditor/base_state.py
flask_ueditor/config_manager.py
flask_ueditor/qiniuyun.py
flask_ueditor/state.py
flask_ueditor/ueditor_json.py
flask_ueditor/uploader.py
flask_ueditor/utils.py
Flask_Ueditor-0.1.0.dist-info/LICENSE
Flask_Ueditor-0.1.0.dist-info/METADATA
Flask_Ueditor-0.1.0.dist-info/WHEEL
Flask_Ueditor-0.1.0.dist-info/top_level.txt
Flask_Ueditor-0.1.0.dist-info/RECORD
