Metadata-Version: 2.1
Name: Flask-Ueditor
Version: 0.1.0
Summary: Flask ueditor Backstage, designed by yy
Home-page: https://github.com/guaidashu/ueditor-flask
Author: guaidashu
Author-email: song42960@gmail.com
License: MIT
Platform: UNKNOWN
Classifier: Topic :: Internet :: WWW/HTTP :: Dynamic Content
Classifier: Programming Language :: Python :: 3
Classifier: Programming Language :: Python :: 3.5
Classifier: Programming Language :: Python :: 3.5
Classifier: Programming Language :: Python :: 3.6
Classifier: Programming Language :: Python :: 3.7
Requires-Dist: qiniu (>=7.2.6)
Requires-Dist: requests (>=2.21.0)
Requires-Dist: Flask (>=1.0.2)
